exercises/Exercise1/exercise1_1.v
module exercise1_1(W,X,Y,Z);
    output[3:0] W; //4bit vector, depth of 1
    input X,Y;
    input Z;
    wire X1,Y1,Z1;

    not G1(X1,X);
    not G2(Y1,Y);
    not G3(Z1,Z);
    nand G4(W[0],X1,Y1,Z1), G5(W[1],X1,Y,Z1), G6(W[2],X,Y1,Z1), G7(W[3],X,Y,Z1);
endmodule

module testbench1_1;

	reg X,Y,Z;
	wire [0:3]W;
	exercise1_1 tb1(W, X, Y, Z);
	
    initial
        begin
            $dumpfile("exercise1_1.vcd");
	        $dumpvars(-1, tb1);
	        $monitor("%b", Z);
        end
	
	initial
	begin
	 X=1'b0; Y=1'b0; Z=1'b0;
	 $display("Simulating output for circuit1_1");

	 #2 X=1'b0; Y=1'b0; Z=1'b1;
	 #1 X=1'b0; Y=1'b1; Z=1'b0;
	 #1 X=1'b0; Y=1'b1; Z=1'b1;
	 #1 X=1'b1; Y=1'b0; Z=1'b0;
	 #1 X=1'b1; Y=1'b0; Z=1'b1;
	 #1 X=1'b1; Y=1'b1; Z=1'b0;
	 #1 X=1'b1; Y=1'b1; Z=1'b1;
	 #2 $finish;
	end
endmodule

exercises/Exercise1/exercise1_1.vcd
$date
	Sun Oct 09 22:52:05 2022
$end
$version
	Icarus Verilog
$end
$timescale
	1s
$end
$scope module testbench1_1 $end
$scope module tb1 $end
$var wire 1 ! X $end
$var wire 1 " X1 $end
$var wire 1 # Y $end
$var wire 1 $ Y1 $end
$var wire 1 % Z $end
$var wire 1 & Z1 $end
$var wire 4 ' W [3:0] $end
$upscope $end
$upscope $end
$enddefinitions $end
$comment Show the parameter values. $end
$dumpall
$end
#0
$dumpvars
b1110 '
1&
0%
1$
0#
1"
0!
$end
#2
b1111 '
0&
1%
#3
b1101 '
1&
0$
0%
1#
#4
b1111 '
0&
1%
#5
b1011 '
1&
1$
0"
0%
0#
1!
#6
b1111 '
0&
1%
#7
b111 '
1&
0$
0%
1#
#8
b1111 '
0&
1%
